LICENSE
MANIFEST.in
README.rst
contributors.txt
setup.py
tox.ini
django_roberts.egg-info/PKG-INFO
django_roberts.egg-info/SOURCES.txt
django_roberts.egg-info/dependency_links.txt
django_roberts.egg-info/top_level.txt
robots/__init__.py
robots/_testrunner.py
robots/models.py
robots/tests.py
robots/urls.py
robots/templates/robots/meta_robots.html
robots/templates/robots/robots.txt