Metadata-Version: 1.1
Name: django-roberts
Version: 0.1.3
Summary: A simple Django app to provide access to a robots.txt file
Home-page: https://bitbucket.org/mhurt/django-roberts
Author: Mike Hurt
Author-email: mike@mhtechnical.net
License: MIT
Keywords: django robots.txt
Platform: UNKNOWN
Classifier: Development Status :: 5 - Production/Stable
Classifier: Environment :: Web Environment
Classifier: Framework :: Django
Classifier: Operating System :: OS Independent
Classifier: Programming Language :: Python
Classifier: Programming Language :: Python :: 2
Classifier: Programming Language :: Python :: 3
Classifier: Topic :: Utilities
Classifier: License :: OSI Approved :: MIT License
